textfile/__init__.py
textfile-0.1.5.dist-info/METADATA
textfile-0.1.5.dist-info/WHEEL
textfile-0.1.5.dist-info/RECORD
