Metadata-Version: 2.1
Name: textfile
Version: 0.1.5
Summary: Functions that enables us to write out or read from with text file in shorter syntax.
Home-page: https://jimaru.site/textfile/
License: MIT
Keywords: text,file,oneline,write,read
Author: kenjimaru
Author-email: kendimaru2@gmail.com
Maintainer: kenjimaru
Maintainer-email: kendimaru2@gmail.com
Requires-Python: >=3.7,<4.0
Classifier: License :: OSI Approved :: MIT License
Classifier: Programming Language :: Python :: 3
Classifier: Programming Language :: Python :: 3.7
Classifier: Programming Language :: Python :: 3.8
Classifier: Programming Language :: Python :: 3.9
Classifier: Programming Language :: Python :: 3.10
Classifier: Programming Language :: Python :: 3.11
Classifier: Programming Language :: Python :: 3.10
Classifier: Programming Language :: Python :: 3.11
Classifier: Programming Language :: Python :: 3.12
Classifier: Programming Language :: Python :: 3.7
Classifier: Programming Language :: Python :: 3.8
Classifier: Programming Language :: Python :: 3.9
Project-URL: Repository, https://github.com/kendimaru/textfile
